{
  "raguilera82": {
    "login": "raguilera82",
    "id": 818068,
    "avatar_url": "https://avatars.githubusercontent.com/u/818068?v=3",
    "gravatar_id": "",
    "url": "https://api.github.com/users/raguilera82",
    "html_url": "https://github.com/raguilera82",
    "followers_url": "https://api.github.com/users/raguilera82/followers",
    "following_url": "https://api.github.com/users/raguilera82/following{/other_user}",
    "gists_url": "https://api.github.com/users/raguilera82/gists{/gist_id}",
    "starred_url": "https://api.github.com/users/raguilera82/starred{/owner}{/repo}",
    "subscriptions_url": "https://api.github.com/users/raguilera82/subscriptions",
    "organizations_url": "https://api.github.com/users/raguilera82/orgs",
    "repos_url": "https://api.github.com/users/raguilera82/repos",
    "events_url": "https://api.github.com/users/raguilera82/events{/privacy}",
    "received_events_url": "https://api.github.com/users/raguilera82/received_events",
    "type": "User",
    "site_admin": false,
    "name": "Rubén Aguilera Díaz-Heredero",
    "company": "Autentia",
    "blog": "http://www.adictosaltrabajo.com",
    "location": "San Fernando de Henares",
    "email": "raguilera@autentia.com",
    "hireable": null,
    "bio": null,
    "public_repos": 29,
    "public_gists": 2,
    "followers": 15,
    "following": 0,
    "created_at": "2011-05-30T06:27:46Z",
    "updated_at": "2016-11-09T19:56:20Z"
  },
  "mojombo": {
    "login": "mojombo",
    "id": 1,
    "avatar_url": "https://avatars.githubusercontent.com/u/1?v=3",
    "gravatar_id": "",
    "url": "https://api.github.com/users/mojombo",
    "html_url": "https://github.com/mojombo",
    "followers_url": "https://api.github.com/users/mojombo/followers",
    "following_url": "https://api.github.com/users/mojombo/following{/other_user}",
    "gists_url": "https://api.github.com/users/mojombo/gists{/gist_id}",
    "starred_url": "https://api.github.com/users/mojombo/starred{/owner}{/repo}",
    "subscriptions_url": "https://api.github.com/users/mojombo/subscriptions",
    "organizations_url": "https://api.github.com/users/mojombo/orgs",
    "repos_url": "https://api.github.com/users/mojombo/repos",
    "events_url": "https://api.github.com/users/mojombo/events{/privacy}",
    "received_events_url": "https://api.github.com/users/mojombo/received_events",
    "type": "User",
    "site_admin": false,
    "name": "Tom Preston-Werner",
    "company": null,
    "blog": "http://tom.preston-werner.com",
    "location": "San Francisco",
    "email": "tom@mojombo.com",
    "hireable": null,
    "bio": null,
    "public_repos": 60,
    "public_gists": 62,
    "followers": 19742,
    "following": 11,
    "created_at": "2007-10-20T05:24:19Z",
    "updated_at": "2016-09-29T10:21:17Z"
  },
  "defunkt": {
    "login": "defunkt",
    "id": 2,
    "avatar_url": "https://avatars.githubusercontent.com/u/2?v=3",
    "gravatar_id": "",
    "url": "https://api.github.com/users/defunkt",
    "html_url": "https://github.com/defunkt",
    "followers_url": "https://api.github.com/users/defunkt/followers",
    "following_url": "https://api.github.com/users/defunkt/following{/other_user}",
    "gists_url": "https://api.github.com/users/defunkt/gists{/gist_id}",
    "starred_url": "https://api.github.com/users/defunkt/starred{/owner}{/repo}",
    "subscriptions_url": "https://api.github.com/users/defunkt/subscriptions",
    "organizations_url": "https://api.github.com/users/defunkt/orgs",
    "repos_url": "https://api.github.com/users/defunkt/repos",
    "events_url": "https://api.github.com/users/defunkt/events{/privacy}",
    "received_events_url": "https://api.github.com/users/defunkt/received_events",
    "type": "User",
    "site_admin": true,
    "name": "Chris Wanstrath",
    "company": "@github ",
    "blog": "http://chriswanstrath.com/",
    "location": "San Francisco",
    "email": "chris@github.com",
    "hireable": true,
    "bio": "🍔 ",
    "public_repos": 107,
    "public_gists": 273,
    "followers": 15784,
    "following": 208,
    "created_at": "2007-10-20T05:24:19Z",
    "updated_at": "2016-09-13T19:41:49Z"
  },
  "pjhyett": {
    "login": "pjhyett",
    "id": 3,
    "avatar_url": "https://avatars.githubusercontent.com/u/3?v=3",
    "gravatar_id": "",
    "url": "https://api.github.com/users/pjhyett",
    "html_url": "https://github.com/pjhyett",
    "followers_url": "https://api.github.com/users/pjhyett/followers",
    "following_url": "https://api.github.com/users/pjhyett/following{/other_user}",
    "gists_url": "https://api.github.com/users/pjhyett/gists{/gist_id}",
    "starred_url": "https://api.github.com/users/pjhyett/starred{/owner}{/repo}",
    "subscriptions_url": "https://api.github.com/users/pjhyett/subscriptions",
    "organizations_url": "https://api.github.com/users/pjhyett/orgs",
    "repos_url": "https://api.github.com/users/pjhyett/repos",
    "events_url": "https://api.github.com/users/pjhyett/events{/privacy}",
    "received_events_url": "https://api.github.com/users/pjhyett/received_events",
    "type": "User",
    "site_admin": true,
    "name": "PJ Hyett",
    "company": "GitHub, Inc.",
    "blog": "https://hyett.com",
    "location": "San Francisco",
    "email": "pj@hyett.com",
    "hireable": null,
    "bio": null,
    "public_repos": 8,
    "public_gists": 21,
    "followers": 8207,
    "following": 30,
    "created_at": "2008-01-07T17:54:22Z",
    "updated_at": "2016-10-16T09:20:26Z"
  },
  "users": [
    {
      "login": "mojombo",
      "id": 1,
      "avatar_url": "https://avatars.githubusercontent.com/u/1?v=3",
      "gravatar_id": "",
      "url": "https://api.github.com/users/mojombo",
      "html_url": "https://github.com/mojombo",
      "followers_url": "https://api.github.com/users/mojombo/followers",
      "following_url": "https://api.github.com/users/mojombo/following{/other_user}",
      "gists_url": "https://api.github.com/users/mojombo/gists{/gist_id}",
      "starred_url": "https://api.github.com/users/mojombo/starred{/owner}{/repo}",
      "subscriptions_url": "https://api.github.com/users/mojombo/subscriptions",
      "organizations_url": "https://api.github.com/users/mojombo/orgs",
      "repos_url": "https://api.github.com/users/mojombo/repos",
      "events_url": "https://api.github.com/users/mojombo/events{/privacy}",
      "received_events_url": "https://api.github.com/users/mojombo/received_events",
      "type": "User",
      "site_admin": false
    },
    {
      "login": "defunkt",
      "id": 2,
      "avatar_url": "https://avatars.githubusercontent.com/u/2?v=3",
      "gravatar_id": "",
      "url": "https://api.github.com/users/defunkt",
      "html_url": "https://github.com/defunkt",
      "followers_url": "https://api.github.com/users/defunkt/followers",
      "following_url": "https://api.github.com/users/defunkt/following{/other_user}",
      "gists_url": "https://api.github.com/users/defunkt/gists{/gist_id}",
      "starred_url": "https://api.github.com/users/defunkt/starred{/owner}{/repo}",
      "subscriptions_url": "https://api.github.com/users/defunkt/subscriptions",
      "organizations_url": "https://api.github.com/users/defunkt/orgs",
      "repos_url": "https://api.github.com/users/defunkt/repos",
      "events_url": "https://api.github.com/users/defunkt/events{/privacy}",
      "received_events_url": "https://api.github.com/users/defunkt/received_events",
      "type": "User",
      "site_admin": true
    },
    {
      "login": "pjhyett",
      "id": 3,
      "avatar_url": "https://avatars.githubusercontent.com/u/3?v=3",
      "gravatar_id": "",
      "url": "https://api.github.com/users/pjhyett",
      "html_url": "https://github.com/pjhyett",
      "followers_url": "https://api.github.com/users/pjhyett/followers",
      "following_url": "https://api.github.com/users/pjhyett/following{/other_user}",
      "gists_url": "https://api.github.com/users/pjhyett/gists{/gist_id}",
      "starred_url": "https://api.github.com/users/pjhyett/starred{/owner}{/repo}",
      "subscriptions_url": "https://api.github.com/users/pjhyett/subscriptions",
      "organizations_url": "https://api.github.com/users/pjhyett/orgs",
      "repos_url": "https://api.github.com/users/pjhyett/repos",
      "events_url": "https://api.github.com/users/pjhyett/events{/privacy}",
      "received_events_url": "https://api.github.com/users/pjhyett/received_events",
      "type": "User",
      "site_admin": true
    }
  ]
}